himena_lmfit/__init__.py
himena_lmfit/_lazy_import.py
himena_lmfit/consts.py
himena_lmfit/io.py
himena_lmfit/_magicgui/__init__.py
himena_lmfit/_magicgui/param.py
himena_lmfit/tools/__init__.py
himena_lmfit/tools/core.py
himena_lmfit/tools/models.py
himena_lmfit/widgets/__init__.py
himena_lmfit/widgets/model.py
himena_lmfit/widgets/model_result.py
himena_lmfit/widgets/parameters.py
himena_lmfit-0.1.0.dist-info/METADATA
himena_lmfit-0.1.0.dist-info/WHEEL
himena_lmfit-0.1.0.dist-info/entry_points.txt
himena_lmfit-0.1.0.dist-info/licenses/LICENSE
himena_lmfit-0.1.0.dist-info/RECORD
